time_checker/__init__.py
time_checker/timer.py
time_checker-0.0.7.dist-info/METADATA
time_checker-0.0.7.dist-info/WHEEL
time_checker-0.0.7.dist-info/top_level.txt
time_checker-0.0.7.dist-info/RECORD
