Metadata-Version: 2.1
Name: time-checker
Version: 0.0.7
Summary: A reusable timer utility for Python programming
Author: Deep Korat
Author-email: deepkorat13@gmail.com
Classifier: Programming Language :: Python :: 3
Classifier: License :: OSI Approved :: MIT License
Classifier: Operating System :: OS Independent
Requires-Python: >=3.6
